group4package/.ipynb_checkpoints/function_count_plot-checkpoint.py
group4package/.ipynb_checkpoints/metrics_function-checkpoint.py
group4package/.ipynb_checkpoints/preprocess-checkpoint.py
group4package/__init__.py
group4package/function_count_plot.py
group4package/group4package.py
group4package/metrics_function copy.py
group4package/metrics_function.py
group4package/preprocess.py
group4package/summary_stats_function.py
group4package-0.1.3.dist-info/LICENSE
group4package-0.1.3.dist-info/WHEEL
group4package-0.1.3.dist-info/METADATA
group4package-0.1.3.dist-info/RECORD
