Metadata-Version: 2.1
Name: group4package
Version: 0.1.3
Summary: Package containing functions to run Group 4's Data Analysis
License: MIT
Author: Hannah, Diana, Jordan, Shravan 
Requires-Python: >=3.9,<3.11
Classifier: License :: OSI Approved :: MIT License
Classifier: Programming Language :: Python :: 3
Classifier: Programming Language :: Python :: 3.10
Classifier: Programming Language :: Python :: 3.9
Requires-Dist: argparse (>=1.4.0,<2.0.0)
Requires-Dist: matplotlib (==3.5.1)
Requires-Dist: numpy (==1.21.5)
Requires-Dist: pandas (>=1.4.2)
Requires-Dist: pandoc (>=2.1,<3.0)
Requires-Dist: plotly (>=5.6.0,<6.0.0)
Requires-Dist: scikit-learn (>=1.0.2,<2.0.0)
Requires-Dist: seaborn (>=0.11.2,<0.12.0)
